{"Id":"-161715235_13","ContentLinks":["https:\/\/pp.userapi.com\/c840634\/v840634853\/54f95\/JSfJ6niDZec.jpg"]}{"Id":"-109125388_191506","ContentLinks":["https:\/\/sun1-19.userapi.com\/c845017\/v845017552\/1f056a\/GG3vEhnYoPw.jpg","https:\/\/sun1-30.userapi.com\/c845017\/v845017552\/1f0553\/_SCPjbvkwPE.jpg","https:\/\/sun1-20.userapi.com\/c845017\/v845017552\/1f0546\/uhR0EFSrzI8.jpg","https:\/\/sun1-28.userapi.com\/c850720\/v850720761\/100c99\/iwrYEMvZD4Q.jpg","https:\/\/sun1-16.userapi.com\/c845017\/v845017552\/1f055d\/KcHg0ePnHoo.jpg","https:\/\/sun1-22.userapi.com\/c845017\/v845017552\/1f057b\/CEV6lXmowVg.jpg","https:\/\/sun1-24.userapi.com\/c845017\/v845017552\/1f0574\/iwYuW4_6MNU.jpg"]}{"Id":"-27902394_798119","ContentLinks":["https:\/\/sun1-15.userapi.com\/c849324\/v849324285\/170def\/8cL0MCAZYHs.jpg"]}{"Id":"-102078234_520227","ContentLinks":["https:\/\/sun1-27.userapi.com\/c7003\/v7003163\/62ffd\/QydgGN34llw.jpg"]}{"Id":"-102078234_519562","ContentLinks":["https:\/\/sun1-28.userapi.com\/c7003\/v7003775\/61a34\/tlpzU9GpfZo.jpg","https:\/\/pp.userapi.com\/c7003\/v7003775\/61a37\/hiLIh1w98CE.jpg"]}{"Id":"-161715235_100","ContentLinks":null}{"Id":"-178745377_454","ContentLinks":["https:\/\/pp.userapi.com\/c855632\/v855632319\/289a0\/gNqK4tvuslc.jpg"]}{"Id":"-109125388_191539","ContentLinks":["https:\/\/sun1-21.userapi.com\/c844720\/v844720188\/1eaafb\/IWIAWVSWTO4.jpg","https:\/\/sun1-15.userapi.com\/c846523\/v846523581\/1c4343\/8c7fQ7fZI4o.jpg","https:\/\/sun1-28.userapi.com\/c844720\/v844720188\/1eaad3\/YuNfUrKFTfU.jpg","https:\/\/sun1-28.userapi.com\/c844720\/v844720188\/1eaada\/JaWET2sZtIs.jpg","https:\/\/sun1-86.userapi.com\/c844720\/v844720188\/1eaae2\/BcSNpCvG5F4.jpg","https:\/\/sun1-27.userapi.com\/c844720\/v844720188\/1eab0e\/c4s47OaRQVo.jpg","https:\/\/sun1-88.userapi.com\/c844720\/v844720188\/1eab1d\/CA1p1U7A68c.jpg","https:\/\/sun1-88.userapi.com\/c846121\/v846121686\/176222\/mP4s0giXsTQ.jpg"]}{"Id":"-102078234_519731","ContentLinks":["https:\/\/sun1-16.userapi.com\/c849420\/v849420795\/17aca4\/dlaALdrHULk.jpg"]}{"Id":"-102078234_519647","ContentLinks":["https:\/\/sun1-87.userapi.com\/c846124\/v846124383\/1f0841\/mjzhIyRzc_g.jpg"]}
nЗдесь был images.json