{
  "Id": "-127903743_232575",
  "ContentText": null
}{
  "Id": "-67171472_43629",
  "ContentText": null
}{
  "Id": "-67171472_43632",
  "ContentText": null
}{
  "Id": "-102078234_515239",
  "ContentText": "Juice WRLD — «Pause»\u000d\u000a\u000d\u000a«Pause» — классическая по своему звучанию и текстовой составляющей композиция Джуси, которая, конечно же, была слита в сеть неизвестными.\u000d\u000a\u000d\u000aБит предоставил 12 Hunna."
}{
  "Id": "-109125388_187865",
  "ContentText": "мемы про сраную черную дыру"
}{
  "Id": "-102078234_515217",
  "ContentText": "Tame Impala — «Borderline»\u000d\u000a\u000d\u000aНовая композиция от австралийской группы Tame Impala — это красивые рассуждения о любви и отношениях.\u000d\u000a\u000d\u000aАльбом коллектива, похоже, уже совсем близко."
}{
  "Id": "-102078234_515207",
  "ContentText": "Joji для «Clash»."
}